faba/__init__.py
faba/_version.py
faba/command.py
faba/exception.py
faba/flag.py
faba-0.0.4.dist-info/LICENSE
faba-0.0.4.dist-info/METADATA
faba-0.0.4.dist-info/WHEEL
faba-0.0.4.dist-info/top_level.txt
faba-0.0.4.dist-info/RECORD
