Metadata-Version: 2.1
Name: faba
Version: 0.0.4
Author-email: Lindasy Zhou <i@lin.moe>
License: Affero General Public License GPL v3 (AGPLv3)
Project-URL: Homepage, https://git.sr.ht/~lindsay/faba
Keywords: arguments parse
Classifier: Programming Language :: Python :: 3.10
Requires-Python: >=3.7
License-File: LICENSE
